easycolor/__init__.py
easycolor/parser.py
easycolor/style.py
easycolor-0.1.dist-info/DESCRIPTION.rst
easycolor-0.1.dist-info/METADATA
easycolor-0.1.dist-info/RECORD
easycolor-0.1.dist-info/WHEEL
easycolor-0.1.dist-info/metadata.json
easycolor-0.1.dist-info/top_level.txt
